single_mol/__init__.py
single_mol/single_mol.py
single_mol-0.1.1.dist-info/LICENSE
single_mol-0.1.1.dist-info/WHEEL
single_mol-0.1.1.dist-info/METADATA
single_mol-0.1.1.dist-info/RECORD
