Metadata-Version: 2.1
Name: single-mol
Version: 0.1.1
Summary: A package to accompany the Single Molecule Counting Perspective.
License: Apache-2.0
Author: Danielle A. Faivre
Requires-Python: >=3.9
Classifier: License :: OSI Approved :: Apache Software License
Classifier: Programming Language :: Python :: 3
Classifier: Programming Language :: Python :: 3.9
Classifier: Programming Language :: Python :: 3.10
Classifier: Programming Language :: Python :: 3.11
Requires-Dist: ipykernel (>=6.19.4)
Requires-Dist: msions (>=0.3.1)
Requires-Dist: pandas (>=1.5.2)
Requires-Dist: pymzml (>=2.5.2)
